{
   "image_to_entry": {
      "pyronear_valbonne_3_2023_11_02T06_50_58.jpg": {
         "image_name": "pyronear_valbonne_3_2023_11_02T06_50_58.jpg",
         "bboxs": [
            {
               "xyxy": [
                  1170.6924439197167,
                  400.76328217237295,
                  1206.961629279811,
                  424.9427390791026
               ],
               "timestamp": 1706605264.470658
            }
         ],
         "history_bboxs": [
            {
               "operation": "add",
               "bbox": {
                  "xyxy": [
                     1170.6924439197167,
                     400.76328217237295,
                     1206.961629279811,
                     424.9427390791026
                  ],
                  "timestamp": 1706605264.470658
               }
            }
         ],
         "image_width": 1280,
         "image_height": 720
      },
      "pyronear_valbonne_3_2023_11_02T06_22_56.jpg": {
         "image_name": "pyronear_valbonne_3_2023_11_02T06_22_56.jpg",
         "bboxs": [
            {
               "xyxy": [
                  669.8512909149955,
                  292.89578454332553,
                  946.3852487604287,
                  480.06206088992974
               ],
               "timestamp": 1706605413.053859
            }
         ],
         "history_bboxs": [
            {
               "operation": "add",
               "bbox": {
                  "xyxy": [
                     669.8512909149955,
                     292.89578454332553,
                     946.3852487604287,
                     480.06206088992974
                  ],
                  "timestamp": 1706605413.053859
               }
            }
         ],
         "image_width": 1280,
         "image_height": 720
      },
      "pyronear_valbonne_3_2023_11_02T06_50_55.jpg": {
         "image_name": "pyronear_valbonne_3_2023_11_02T06_50_55.jpg",
         "bboxs": [
            {
               "xyxy": [
                  860.3899326011781,
                  178.23536299765806,
                  968.3056234676886,
                  458.1416861826698
               ],
               "timestamp": 1706605416.440823
            }
         ],
         "history_bboxs": [
            {
               "operation": "add",
               "bbox": {
                  "xyxy": [
                     860.3899326011781,
                     178.23536299765806,
                     968.3056234676886,
                     458.1416861826698
                  ],
                  "timestamp": 1706605416.440823
               }
            }
         ],
         "image_width": 1280,
         "image_height": 720
      },
      "pyronear_valbonne_3_2023_11_02T06_50_57.jpg": {
         "image_name": "pyronear_valbonne_3_2023_11_02T06_50_57.jpg",
         "bboxs": [
            {
               "xyxy": [
                  910.9754126948549,
                  156.3149882903981,
                  953.1299794395856,
                  469.9449648711944
               ],
               "timestamp": 1706605418.524412
            }
         ],
         "history_bboxs": [
            {
               "operation": "add",
               "bbox": {
                  "xyxy": [
                     910.9754126948549,
                     156.3149882903981,
                     953.1299794395856,
                     469.9449648711944
                  ],
                  "timestamp": 1706605418.524412
               }
            }
         ],
         "image_width": 1280,
         "image_height": 720
      }
   }
}